{
  "generated_at": "2026-04-22T18:28:13.611295-04:00",
  "event_key": "2026-04-22|La Suerte|Quiniela La Suerte 6PM",
  "items": [
    {
      "generated_at": "2026-04-22T18:28:12.985850-04:00",
      "event_key": "2026-04-22|La Suerte|Quiniela La Suerte 6PM",
      "target": {
        "time_rd": "2026-04-22 19:00",
        "lottery": "La Primera",
        "draw": "Quiniela La Primera Noche"
      },
      "best_play": {
        "time_rd": "2026-04-22 19:00",
        "lottery": "La Primera",
        "draw": "Quiniela La Primera Noche",
        "top12": [
          "58",
          "03",
          "18",
          "41",
          "31",
          "14",
          "79",
          "99",
          "05",
          "54",
          "55",
          "15"
        ],
        "topq": [
          "58",
          "03",
          "18"
        ],
        "pales": [
          "03-58",
          "18-58",
          "41-58"
        ],
        "fingerprint": "752230d7077467a4",
        "ok_alert": false,
        "best_signal": 0.0014833885159800178,
        "best_a11": 9,
        "debug": {
          "best_signal_hist": 0.0014833885159800178,
          "best_a11_hist": 9,
          "has_intraday_sources": 0,
          "intraday_events": 0,
          "today_observed_nums": 20,
          "source_pairs_today": 7,
          "source_rows_hist_used": 4689
        }
      }
    }
  ]
}